znbstatic/__init__.py
znbstatic/admin.py
znbstatic/apps.py
znbstatic/context_processors.py
znbstatic/models.py
znbstatic/storage.py
znbstatic/utils.py
znbstatic/views.py
znbstatic/__pycache__/__init__.cpython-37.pyc
znbstatic/__pycache__/__init__.cpython-38.pyc
znbstatic/__pycache__/admin.cpython-37.pyc
znbstatic/__pycache__/apps.cpython-37.pyc
znbstatic/__pycache__/context_processors.cpython-37.pyc
znbstatic/__pycache__/models.cpython-37.pyc
znbstatic/__pycache__/storage.cpython-37.pyc
znbstatic/__pycache__/utils.cpython-37.pyc
znbstatic/static/znbstatic/znbstatic-placeholder.html
znbstatic/templates/znbstatic/test.html
znbstatic/templatetags/__init__.py
znbstatic/templatetags/znbstatic.py
znbstatic/templatetags/__pycache__/__init__.cpython-37.pyc
znbstatic/templatetags/__pycache__/znbstatic.cpython-37.pyc
znbstatic-0.6.dist-info/AUTHORS
znbstatic-0.6.dist-info/LICENSE
znbstatic-0.6.dist-info/METADATA
znbstatic-0.6.dist-info/WHEEL
znbstatic-0.6.dist-info/top_level.txt
znbstatic-0.6.dist-info/RECORD
